Metadata-Version: 1.1
Name: binpacker
Version: 0.1.3
Summary: Distribute weighted tasks equally to workers by solving Bin Packing problem. This package provides an abstraction for user to extend
Home-page: https://github.com/pkuong/binpacker
Author: Paulo Kuong
Author-email: paulo.kuong@gmail.com
License: MIT
Keywords: algorithm bin packing shipping inventory warehouse transportation distribution parallel
Platform: UNKNOWN
Classifier: Development Status :: 3 - Alpha
Classifier: License :: OSI Approved :: MIT License
Classifier: Programming Language :: Python :: 3.4
